wolfsoftware/prereqs/__init__.py
wolfsoftware/prereqs/exceptions.py
wolfsoftware/prereqs/prerequisite_checker.py
wolfsoftware.prereqs-0.1.5.dist-info/LICENSE.md
wolfsoftware.prereqs-0.1.5.dist-info/METADATA
wolfsoftware.prereqs-0.1.5.dist-info/WHEEL
wolfsoftware.prereqs-0.1.5.dist-info/top_level.txt
wolfsoftware.prereqs-0.1.5.dist-info/RECORD
