Metadata-Version: 2.1
Name: wolfsoftware.prereqs
Version: 0.1.5
Summary: Check for the presence of prerequisite commands and returns their paths.
Home-page: https://github.com/DevelopersToolbox/check-prerequisite-package
Author: Wolf Software
Author-email: pypi@wolfsoftware.com
License: MIT
Project-URL: Source, https://github.com/DevelopersToolbox/check-prerequisite-package
Project-URL: Tracker, https://github.com/DevelopersToolbox/check-prerequisite-package/issues/
Project-URL: Documentation, https://github.com/DevelopersToolbox/check-prerequisite-package
Project-URL: Sponsor, https://github.com/sponsors/WolfSoftware
Keywords: python,prereqs
Classifier: Development Status :: 4 - Beta
Classifier: Environment :: Console
Classifier: Intended Audience :: Developers
Classifier: License :: OSI Approved :: MIT License
Classifier: Programming Language :: Python :: 3
Classifier: Programming Language :: Python :: 3.9
Classifier: Programming Language :: Python :: 3.10
Classifier: Programming Language :: Python :: 3.11
Classifier: Programming Language :: Python :: 3.12
Classifier: Operating System :: OS Independent
Classifier: Topic :: Software Development
Requires-Python: >=3.9
License-File: LICENSE.md
